PCA9685_wrapper/PCA9685_wrapper.py
PCA9685_wrapper/__init__.py
PCA9685_wrapper-0.0.5.dist-info/LICENSE
PCA9685_wrapper-0.0.5.dist-info/METADATA
PCA9685_wrapper-0.0.5.dist-info/WHEEL
PCA9685_wrapper-0.0.5.dist-info/top_level.txt
PCA9685_wrapper-0.0.5.dist-info/RECORD
