Metadata-Version: 2.1
Name: PCA9685-wrapper
Version: 0.0.5
Summary: adafruit-pca9685 wrapper for Raspberry pi
Home-page: https://github.com/being24/PCA9685_Wrapper
Author: being24
Author-email: being24@gmail.com
License: UNKNOWN
Platform: UNKNOWN
Classifier: Programming Language :: Python :: 3.8
Classifier: License :: OSI Approved :: MIT License
License-File: LICENSE
Requires-Dist: adafruit-pca9685
